torch_pso/__init__.py
torch_pso/optim/AcceleratedPSO.py
torch_pso/optim/AutotuningPSO.py
torch_pso/optim/ChaoticPSO.py
torch_pso/optim/GenerationalPSO.py
torch_pso/optim/GenericPSO.py
torch_pso/optim/ImprovedSineCosineAlgorithm.py
torch_pso/optim/ParticleSwarmOptimizer.py
torch_pso/optim/RingTopologyPSO.py
torch_pso/optim/SineCosineAlgorithm.py
torch_pso/optim/__init__.py
torch_pso-1.2.1.dist-info/METADATA
torch_pso-1.2.1.dist-info/WHEEL
torch_pso-1.2.1.dist-info/licenses/LICENSE
torch_pso-1.2.1.dist-info/RECORD
