Metadata-Version: 2.1
Name: torch_pso
Version: 1.2.1
Summary: Particle Swarm Optimization using the torch.optim API.
Project-URL: repository, https://github.com/qthequartermasterman/torch_pso
Author-email: Andrew Sansom <andrew@euleriancircuit.com>
License: Copyright 2022 Andrew Sansom
Keywords: optimizer,particle swarm,pytorch
Classifier: License :: OSI Approved :: MIT License
Classifier: Programming Language :: Python
Classifier: Programming Language :: Python :: 3
Requires-Python: >=3.7
Requires-Dist: torch
